{
    "text_id": 4,
    "chats": [],
    "options": [
        {
            "text": "“目前的严峻局势”",
            "chats": [
                {
                    "name": "我",
                    "text": "我们都知道，我们正经受着前所未有的困难，今天，我们的国家正在分崩离析，承担着高额的债务，人民无法安居乐业，我们在这种严峻的形势下受苦受难。"
                }
            ],
            "action": [],
            "next_text": 5
        },
        {
            "text": "谢云的号召”",
            "chats": [
                {
                    "name": "我",
                    "text": "我们都知道，我们的国家今非昔比。在谢云的领导下，我们取得了辉煌的成就。从落后挨打到取得认可，我们珂洛再一次实现了昔日的辉煌。如今我们应该继续团结在这面旗帜下，继承谢云的思想。"
                }
            ],
            "action": [],
            "next_text": 5
        },
        {
            "text": "“重生与希望”",
            "chats": [
                {
                    "name": "我",
                    "text": "我们都知道，昔日的屈辱历史将一笔划去。人民和历史已经做出了选择。我们将共同为国家带来繁荣和改革。这是一个变革的时代，是一个充满希望的时代。"
                }
            ],
            "action": [],
            "next_text": 5
        }
    ]
}